{
    "meta": {
        "id": "IREF378343",
        "prepared": "2023-04-17T13:23:53",
        "test": false,
        "datasetId": "750aac1b-ab16-45f2-8706-77cae63018c0",
        "sender": {
            "id": "Unknown"
        },
        "receiver": {
            "id": "guest"
        },
        "links": [
            {
                "rel": "self",
                "href": "/data/EXR/B..NOK.SP?format=sdmx-json&lastNObservations=1&locale=en",
                "uri": "https://raw.githubusercontent.com/sdmx-twg/sdmx-json/develop/structure-message/tools/schemas/1.0/sdmx-json-structure-schema.json"
            }
        ]
    },
    "data": {
        "dataSets": [
            {
                "links": [
                    {
                        "rel": "dataflow",
                        "urn": "urn:sdmx:org.sdmx.infomodel.datastructure.Dataflow=NB:EXR(1.0)"
                    }
                ],
                "action": "Information",
                "series": {
                    "0:0:0:0": {
                        "attributes": [
                            0,
                            0,
                            0,
                            0
                        ],
                        "observations": {
                            "0": [
                                "3.0513"
                            ]
                        }
                    },
                    "0:1:0:0": {
                        "attributes": [
                            1,
                            0,
                            0,
                            0
                        ],
                        "observations": {
                            "0": [
                                "153.03"
                            ]
                        }
                    },
                    "0:2:0:0": {
                        "attributes": [
                            2,
                            0,
                            0,
                            0
                        ],
                        "observations": {
                            "1": [
                                "8.413"
                            ]
                        }
                    },
                    "0:3:0:0": {
                        "attributes": [
                            0,
                            0,
                            0,
                            0
                        ],
                        "observations": {
                            "0": [
                                "0.491"
                            ]
                        }
                    },
                    "0:4:0:0": {
                        "attributes": [
                            3,
                            1,
                            1,
                            0
                        ],
                        "observations": {
                            "0": [
                                "13.96693"
                            ]
                        }
                    },
                    "0:5:0:0": {
                        "attributes": [
                            1,
                            0,
                            0,
                            0
                        ],
                        "observations": {
                            "0": [
                                "53.23"
                            ]
                        }
                    },
                    "0:6:0:0": {
                        "attributes": [
                            1,
                            0,
                            0,
                            0
                        ],
                        "observations": {
                            "0": [
                                "230.7"
                            ]
                        }
                    },
                    "0:7:0:0": {
                        "attributes": [
                            0,
                            0,
                            1,
                            0
                        ],
                        "observations": {
                            "0": [
                                "6.4828"
                            ]
                        }
                    },
                    "0:8:0:0": {
                        "attributes": [
                            0,
                            0,
                            0,
                            0
                        ],
                        "observations": {
                            "0": [
                                "7.7776"
                            ]
                        }
                    },
                    "0:9:0:0": {
                        "attributes": [
                            0,
                            0,
                            1,
                            0
                        ],
                        "observations": {
                            "0": [
                                "1.3136"
                            ]
                        }
                    },
                    "0:10:0:0": {
                        "attributes": [
                            2,
                            0,
                            0,
                            0
                        ],
                        "observations": {
                            "0": [
                                "48.85"
                            ]
                        }
                    },
                    "0:11:0:0": {
                        "attributes": [
                            0,
                            0,
                            1,
                            0
                        ],
                        "observations": {
                            "0": [
                                "7.7433"
                            ]
                        }
                    },
                    "0:12:0:0": {
                        "attributes": [
                            1,
                            0,
                            0,
                            0
                        ],
                        "observations": {
                            "0": [
                                "9.69"
                            ]
                        }
                    },
                    "0:13:0:0": {
                        "attributes": [
                            0,
                            0,
                            1,
                            0
                        ],
                        "observations": {
                            "0": [
                                "10.312"
                            ]
                        }
                    },
                    "0:14:0:0": {
                        "attributes": [
                            2,
                            0,
                            0,
                            0
                        ],
                        "observations": {
                            "0": [
                                "30.276"
                            ]
                        }
                    },
                    "0:15:0:0": {
                        "attributes": [
                            0,
                            0,
                            1,
                            0
                        ],
                        "observations": {
                            "0": [
                                "2.4555"
                            ]
                        }
                    },
                    "0:16:0:0": {
                        "attributes": [
                            0,
                            0,
                            1,
                            0
                        ],
                        "observations": {
                            "0": [
                                "6.9912"
                            ]
                        }
                    },
                    "0:17:0:0": {
                        "attributes": [
                            0,
                            0,
                            1,
                            0
                        ],
                        "observations": {
                            "0": [
                                "2.3426"
                            ]
                        }
                    },
                    "0:18:0:0": {
                        "attributes": [
                            2,
                            0,
                            0,
                            0
                        ],
                        "observations": {
                            "0": [
                                "12.618"
                            ]
                        }
                    },
                    "0:19:0:0": {
                        "attributes": [
                            4,
                            0,
                            0,
                            0
                        ],
                        "observations": {
                            "0": [
                                "0.069986"
                            ]
                        }
                    },
                    "0:20:0:0": {
                        "attributes": [
                            0,
                            0,
                            1,
                            0
                        ],
                        "observations": {
                            "0": [
                                "12.8924"
                            ]
                        }
                    },
                    "0:21:0:0": {
                        "attributes": [
                            1,
                            0,
                            0,
                            0
                        ],
                        "observations": {
                            "0": [
                                "150.5"
                            ]
                        }
                    },
                    "0:22:0:0": {
                        "attributes": [
                            0,
                            0,
                            1,
                            0
                        ],
                        "observations": {
                            "0": [
                                "2.0956"
                            ]
                        }
                    },
                    "0:23:0:0": {
                        "attributes": [
                            0,
                            0,
                            0,
                            0
                        ],
                        "observations": {
                            "0": [
                                "0.044"
                            ]
                        }
                    },
                    "0:24:0:0": {
                        "attributes": [
                            0,
                            0,
                            1,
                            0
                        ],
                        "observations": {
                            "0": [
                                "4.0846"
                            ]
                        }
                    },
                    "0:25:0:0": {
                        "attributes": [
                            1,
                            1,
                            1,
                            0
                        ],
                        "observations": {
                            "0": [
                                "130.93"
                            ]
                        }
                    },
                    "0:26:0:0": {
                        "attributes": [
                            0,
                            0,
                            1,
                            0
                        ],
                        "observations": {
                            "0": [
                                "7.775"
                            ]
                        }
                    },
                    "0:27:0:0": {
                        "attributes": [
                            2,
                            0,
                            0,
                            0
                        ],
                        "observations": {
                            "0": [
                                "3.666"
                            ]
                        }
                    },
                    "0:28:0:0": {
                        "attributes": [
                            1,
                            0,
                            0,
                            0
                        ],
                        "observations": {
                            "0": [
                                "57.12"
                            ]
                        }
                    },
                    "0:29:0:0": {
                        "attributes": [
                            0,
                            0,
                            1,
                            0
                        ],
                        "observations": {
                            "0": [
                                "2.8205"
                            ]
                        }
                    },
                    "0:30:0:0": {
                        "attributes": [
                            1,
                            1,
                            1,
                            0
                        ],
                        "observations": {
                            "0": [
                                "119.49"
                            ]
                        }
                    },
                    "0:31:0:0": {
                        "attributes": [
                            0,
                            0,
                            1,
                            0
                        ],
                        "observations": {
                            "0": [
                                "11.402"
                            ]
                        }
                    },
                    "0:32:0:0": {
                        "attributes": [
                            1,
                            0,
                            0,
                            0
                        ],
                        "observations": {
                            "0": [
                                "1160.27"
                            ]
                        }
                    },
                    "0:33:0:0": {
                        "attributes": [
                            1,
                            0,
                            0,
                            0
                        ],
                        "observations": {
                            "2": [
                                "139.51"
                            ]
                        }
                    },
                    "0:34:0:0": {
                        "attributes": [
                            1,
                            0,
                            0,
                            0
                        ],
                        "observations": {
                            "0": [
                                "582.98"
                            ]
                        }
                    },
                    "0:35:0:0": {
                        "attributes": [
                            1,
                            0,
                            0,
                            0
                        ],
                        "observations": {
                            "0": [
                                "7.62"
                            ]
                        }
                    },
                    "0:36:0:0": {
                        "attributes": [
                            0,
                            0,
                            1,
                            0
                        ],
                        "observations": {
                            "0": [
                                "0.572"
                            ]
                        }
                    },
                    "0:37:0:0": {
                        "attributes": [
                            2,
                            0,
                            0,
                            0
                        ],
                        "observations": {
                            "0": [
                                "33.857"
                            ]
                        }
                    },
                    "0:38:0:0": {
                        "attributes": [
                            1,
                            0,
                            0,
                            0
                        ],
                        "observations": {
                            "0": [
                                "100.5"
                            ]
                        }
                    },
                    "0:39:0:0": {
                        "attributes": [
                            2,
                            0,
                            0,
                            0
                        ],
                        "observations": {
                            "0": [
                                "18.654"
                            ]
                        }
                    },
                    "0:40:0:0": {
                        "attributes": [
                            0,
                            0,
                            0,
                            0
                        ],
                        "observations": {
                            "0": [
                                "0.7927"
                            ]
                        }
                    }
                }
            }
        ],
        "structure": {
            "links": [
                {
                    "rel": "dataflow",
                    "urn": "urn:sdmx:org.sdmx.infomodel.datastructure.Dataflow=NB:EXR(1.0)"
                },
                {
                    "rel": "datastructure",
                    "urn": "urn:sdmx:org.sdmx.infomodel.datastructure.DataStructure=NB:DSD_EXR(1.0)"
                }
            ],
            "name": "Exchange rates",
            "names": {
                "en": "Exchange rates"
            },
            "description": "Norges Bank exchange rate statistics",
            "descriptions": {
                "en": "Norges Bank exchange rate statistics"
            },
            "dimensions": {
                "dataset": [],
                "series": [
                    {
                        "id": "FREQ",
                        "name": "Frequency",
                        "description": "The time interval at which observations occur\n                        over a given time period.",
                        "keyPosition": 0,
                        "role": null,
                        "values": [
                            {
                                "id": "B",
                                "name": "Business",
                                "description": "Business"
                            }
                        ]
                    },
                    {
                        "id": "BASE_CUR",
                        "name": "Base Currency",
                        "description": "The first currency in a currency pair quotation.\n                        Also known as the transaction currency.",
                        "keyPosition": 1,
                        "role": null,
                        "values": [
                            {
                                "id": "HUF",
                                "name": "Hungarian forint"
                            },
                            {
                                "id": "DKK",
                                "name": "Danish krone"
                            },
                            {
                                "id": "RUB",
                                "name": "Russian rouble"
                            },
                            {
                                "id": "MMK",
                                "name": "Myanmar kyat"
                            },
                            {
                                "id": "XDR",
                                "name": "IMF, special drawing rights"
                            },
                            {
                                "id": "TRY",
                                "name": "Turkish lira"
                            },
                            {
                                "id": "RON",
                                "name": "New Romanian leu"
                            },
                            {
                                "id": "NZD",
                                "name": "New Zealand dollar"
                            },
                            {
                                "id": "JPY",
                                "name": "Japanese yen"
                            },
                            {
                                "id": "HKD",
                                "name": "Hong Kong dollar"
                            },
                            {
                                "id": "CZK",
                                "name": "Czech koruna"
                            },
                            {
                                "id": "CAD",
                                "name": "Canadian dollar"
                            },
                            {
                                "id": "BDT",
                                "name": "Bangladeshi taka"
                            },
                            {
                                "id": "USD",
                                "name": "US dollar"
                            },
                            {
                                "id": "THB",
                                "name": "Thai baht"
                            },
                            {
                                "id": "PLN",
                                "name": "Polish zloty"
                            },
                            {
                                "id": "AUD",
                                "name": "Australian dollar"
                            },
                            {
                                "id": "MYR",
                                "name": "Malaysian ringgit"
                            },
                            {
                                "id": "INR",
                                "name": "Indian rupee"
                            },
                            {
                                "id": "IDR",
                                "name": "Indonesian rupiah"
                            },
                            {
                                "id": "GBP",
                                "name": "Pound sterling"
                            },
                            {
                                "id": "CNY",
                                "name": "Chinese yuan"
                            },
                            {
                                "id": "BRL",
                                "name": "Brazilian real"
                            },
                            {
                                "id": "VND",
                                "name": "Vietnamese dong"
                            },
                            {
                                "id": "BYN",
                                "name": "Belarusian new rouble"
                            },
                            {
                                "id": "TWI",
                                "name": "Trade-weighted krone exchange rate"
                            },
                            {
                                "id": "SGD",
                                "name": "Singapore dollar"
                            },
                            {
                                "id": "PKR",
                                "name": "Pakistani rupee"
                            },
                            {
                                "id": "MXN",
                                "name": "Mexican peso"
                            },
                            {
                                "id": "ILS",
                                "name": "Israeli new shekel"
                            },
                            {
                                "id": "I44",
                                "name": "Import-weighted krone exchange rate"
                            },
                            {
                                "id": "EUR",
                                "name": "Euro"
                            },
                            {
                                "id": "CHF",
                                "name": "Swiss franc"
                            },
                            {
                                "id": "HRK",
                                "name": "Croatian kuna"
                            },
                            {
                                "id": "BGN",
                                "name": "Bulgarian lev"
                            },
                            {
                                "id": "ISK",
                                "name": "Icelandic krona"
                            },
                            {
                                "id": "ZAR",
                                "name": "South African rand"
                            },
                            {
                                "id": "TWD",
                                "name": "New Taiwan dollar"
                            },
                            {
                                "id": "SEK",
                                "name": "Swedish krona"
                            },
                            {
                                "id": "PHP",
                                "name": "Philippine peso"
                            },
                            {
                                "id": "KRW",
                                "name": "South Korean won"
                            }
                        ]
                    },
                    {
                        "id": "QUOTE_CUR",
                        "name": "Quote Currency",
                        "description": "The second currency in a currency quote pair.\n                        Also known as counter currency.",
                        "keyPosition": 2,
                        "role": null,
                        "values": [
                            {
                                "id": "NOK",
                                "name": "Norwegian krone"
                            }
                        ]
                    },
                    {
                        "id": "TENOR",
                        "name": "Tenor",
                        "description": "The amount of time left for the repayment of a\n                        loan or until a financial contract expires.",
                        "keyPosition": 3,
                        "role": null,
                        "values": [
                            {
                                "id": "SP",
                                "name": "Spot"
                            }
                        ]
                    }
                ],
                "observation": [
                    {
                        "id": "TIME_PERIOD",
                        "name": "Time Period",
                        "description": "The period of time or point in time to which the\n                        measured observation refers.",
                        "keyPosition": 4,
                        "role": "time",
                        "values": [
                            {
                                "start": "2023-04-14T00:00:00",
                                "end": "2023-04-14T23:59:59",
                                "id": "2023-04-14",
                                "name": "2023-04-14"
                            },
                            {
                                "start": "2022-03-01T00:00:00",
                                "end": "2022-03-01T23:59:59",
                                "id": "2022-03-01",
                                "name": "2022-03-01"
                            },
                            {
                                "start": "2022-12-30T00:00:00",
                                "end": "2022-12-30T23:59:59",
                                "id": "2022-12-30",
                                "name": "2022-12-30"
                            }
                        ]
                    }
                ]
            },
            "attributes": {
                "dataset": [],
                "series": [
                    {
                        "id": "DECIMALS",
                        "name": "Decimals",
                        "description": "The number of digits to the right of a decimal\n                        point.",
                        "relationship": {
                            "dimensions": [
                                "BASE_CUR",
                                "QUOTE_CUR",
                                "TENOR"
                            ]
                        },
                        "role": null,
                        "values": [
                            {
                                "id": "4",
                                "name": "4"
                            },
                            {
                                "id": "2",
                                "name": "2"
                            },
                            {
                                "id": "3",
                                "name": "3"
                            },
                            {
                                "id": "5",
                                "name": "5"
                            },
                            {
                                "id": "6",
                                "name": "6"
                            }
                        ]
                    },
                    {
                        "id": "CALCULATED",
                        "name": "Calculated",
                        "description": "Indicates if the value is calculated or an actual\n                        observation.",
                        "relationship": {
                            "dimensions": [
                                "BASE_CUR",
                                "QUOTE_CUR",
                                "TENOR"
                            ]
                        },
                        "role": null,
                        "values": [
                            {
                                "id": "false",
                                "name": "false"
                            },
                            {
                                "id": "true",
                                "name": "true"
                            }
                        ]
                    },
                    {
                        "id": "UNIT_MULT",
                        "name": "Unit Multiplier",
                        "description": "Exponent in base 10 specified so that multiplying\n                        the observation numeric values by 10^UNIT_MULT gives a value expressed in\n                        the UNIT.",
                        "relationship": {
                            "dimensions": [
                                "BASE_CUR",
                                "QUOTE_CUR",
                                "TENOR"
                            ]
                        },
                        "role": null,
                        "values": [
                            {
                                "id": "2",
                                "name": "Hundreds"
                            },
                            {
                                "id": "0",
                                "name": "Units"
                            }
                        ]
                    },
                    {
                        "id": "COLLECTION",
                        "name": "Collection Indicator",
                        "description": "Dates or periods during which the observations\n                        have been collected.",
                        "relationship": {
                            "dimensions": [
                                "BASE_CUR",
                                "QUOTE_CUR",
                                "TENOR"
                            ]
                        },
                        "role": null,
                        "values": [
                            {
                                "id": "C",
                                "name": "ECB concertation time 14:15 CET"
                            }
                        ]
                    }
                ],
                "observation": []
            }
        }
    }
}
